EnvCrypt/__init__.py
envcrypt-0.1.1.dist-info/LICENSE
envcrypt-0.1.1.dist-info/METADATA
envcrypt-0.1.1.dist-info/WHEEL
envcrypt-0.1.1.dist-info/top_level.txt
envcrypt-0.1.1.dist-info/RECORD
