Metadata-Version: 2.1
Name: envcrypt
Version: 0.1.1
Summary: A Python library for managing encrypted environment files using Base64 and AES, with support for backups and integrity checks.
Home-page: https://alicrafty1191.github.io/EnvCrypt/
Author: Ali Crafty
Author-email: aaasdujkkofe@gmail.com
Classifier: Programming Language :: Python :: 3
Classifier: License :: OSI Approved :: MIT License
Classifier: Operating System :: OS Independent
Requires-Python: >=3.6
License-File: LICENSE
Requires-Dist: cryptography
